LazyVideoReader/__init__.py
LazyVideoReader/lazy_video_reader.py
LazyVideoReader-0.1.1.dist-info/LICENSE
LazyVideoReader-0.1.1.dist-info/METADATA
LazyVideoReader-0.1.1.dist-info/WHEEL
LazyVideoReader-0.1.1.dist-info/top_level.txt
LazyVideoReader-0.1.1.dist-info/RECORD
