Metadata-Version: 2.1
Name: LazyVideoReader
Version: 0.1.1
Summary: A lazy video loader for working with a huge amount of video frame as numpy array
Home-page: https://github.com/Slownite/Lazy_Video_Reader
Author: Slownite (Samuel Diop)
Author-email: <snfdiop@outlook.com>
License: UNKNOWN
Keywords: python,video,frames extraction,lazy loading,generator
Platform: UNKNOWN
Classifier: Development Status :: 1 - Planning
Classifier: Intended Audience :: Developers
Classifier: Programming Language :: Python :: 3
Classifier: Operating System :: Unix
Classifier: Operating System :: MacOS :: MacOS X
Classifier: Operating System :: Microsoft :: Windows
License-File: LICENSE
Requires-Dist: opencv-python
Requires-Dist: numpy
